cyral/__init__.py
cyral/cli/__init__.py
cyral/cli/__main__.py
cyral/cli/_aws.py
cyral/cli/_help.py
cyral/cli/_options.py
cyral/cli/_pgpass.py
cyral/cli/commands.py
cyral/sdk/__init__.py
cyral/sdk/api/__init__.py
cyral/sdk/api/access_info.py
cyral/sdk/api/access_token.py
cyral/sdk/api/ca_bundle.py
cyral/sdk/api/resource.py
cyral/sdk/api/sidecar.py
cyral/sdk/api/user.py
cyral/sdk/client.py
cyral-2.5.8.dist-info/METADATA
cyral-2.5.8.dist-info/WHEEL
cyral-2.5.8.dist-info/entry_points.txt
cyral-2.5.8.dist-info/RECORD
