Metadata-Version: 2.1
Name: cyral
Version: 2.5.8
Summary: The Cyral CLI tool
License: MIT
Author: Deepak Gupta
Author-email: deepak@cyral.com
Requires-Python: >=3.9,<4.0
Classifier: License :: OSI Approved :: MIT License
Classifier: Programming Language :: Python :: 3
Classifier: Programming Language :: Python :: 3.9
Classifier: Programming Language :: Python :: 3.10
Classifier: Programming Language :: Python :: 3.11
Requires-Dist: PyYAML (>=6.0,<7.0)
Requires-Dist: botocore (>=1.33,<2.0)
Requires-Dist: click (>=8.1,<9.0)
Requires-Dist: columnar (>=1.4,<2.0)
Requires-Dist: iso8601 (>=2.1.0,<3.0.0)
Requires-Dist: oauthlib (>=3.2,<4.0)
Requires-Dist: requests (>=2.31,<3.0)
